mcp_duty_pharma/__about__.py
mcp_duty_pharma/__init__.py
mcp_duty_pharma/__main__.py
mcp_duty_pharma/duty_pharma.py
mcp_duty_pharma/py.typed
mcp_duty_pharma-0.1.17.dist-info/METADATA
mcp_duty_pharma-0.1.17.dist-info/WHEEL
mcp_duty_pharma-0.1.17.dist-info/entry_points.txt
mcp_duty_pharma-0.1.17.dist-info/licenses/LICENCE.md
mcp_duty_pharma-0.1.17.dist-info/RECORD
