Metadata-Version: 2.4
Name: mcp_duty_pharma
Version: 0.1.17
Summary: MCP Duty Pharma helps you locate pharmacies legally required to stay open during nights, weekends, and holidays
Project-URL: Documentation, https://github.com/lsaavedr/mcp-duty-pharma#readme
Project-URL: Issues, https://github.com/lsaavedr/mcp-duty-pharma/issues
Project-URL: Source, https://github.com/lsaavedr/mcp-duty-pharma
Author-email: Luis Saavedra <luis94855510@gmail.com>
License: MIT
License-File: LICENCE.md
Keywords: 24/7,duty,emergency,mcp,open,pharma,pharmacy
Classifier: Development Status :: 4 - Beta
Classifier: Intended Audience :: Developers
Classifier: Programming Language :: Python :: 3
Classifier: Programming Language :: Python :: 3.10
Classifier: Programming Language :: Python :: 3.11
Classifier: Programming Language :: Python :: 3.12
Classifier: Topic :: Software Development :: Build Tools
Requires-Python: >=3.10
Requires-Dist: argparse>=1.4.0
Requires-Dist: geopy>=2.4.1
Requires-Dist: httpx>=0.28.1
Requires-Dist: mcp[cli]>=1.6.0
Requires-Dist: pytz>=2025.2
